iocare/__init__.py
iocare/exceptions.py
iocare/iocareapi.py
iocare/devices/__init__.py
iocare/devices/purifier.py
pyiocare-0.0.3.dist-info/LICENSE
pyiocare-0.0.3.dist-info/METADATA
pyiocare-0.0.3.dist-info/WHEEL
pyiocare-0.0.3.dist-info/top_level.txt
pyiocare-0.0.3.dist-info/RECORD
